{
  "600519.SS": {
    "last": 1444.0,
    "as_of": "2025-09-24T05:01:56Z",
    "interval": "akshare_spot"
  },
  "601318.SS": {
    "last": 55.14,
    "as_of": "2025-09-24T05:03:55Z",
    "interval": "akshare_spot"
  },
  "601398.SS": {
    "last": 7.42,
    "as_of": "2025-09-24T05:05:47Z",
    "interval": "akshare_spot"
  },
  "601288.SS": {
    "last": 6.58,
    "as_of": "2025-09-24T05:07:38Z",
    "interval": "akshare_spot"
  },
  "601988.SS": {
    "last": 5.28,
    "as_of": "2025-09-24T05:09:16Z",
    "interval": "akshare_spot"
  },
  "601857.SS": {
    "last": 8.1,
    "as_of": "2025-09-24T00:00:00Z",
    "interval": "akshare_daily"
  },
  "600028.SS": {
    "last": 5.35,
    "as_of": "2025-09-24T00:00:00Z",
    "interval": "akshare_daily"
  },
  "600036.SS": {
    "last": 41.43,
    "as_of": "2025-09-24T00:00:00Z",
    "interval": "akshare_daily"
  },
  "601166.SS": {
    "last": 20.24,
    "as_of": "2025-09-24T00:00:00Z",
    "interval": "akshare_daily"
  },
  "600900.SS": {
    "last": 27.29,
    "as_of": "2025-09-24T00:00:00Z",
    "interval": "akshare_daily"
  },
  "601888.SS": {
    "last": 70.0,
    "as_of": "2025-09-24T00:00:00Z",
    "interval": "akshare_daily"
  },
  "601012.SS": {
    "last": 16.57,
    "as_of": "2025-09-24T00:00:00Z",
    "interval": "akshare_daily"
  },
  "600104.SS": {
    "last": 17.58,
    "as_of": "2025-09-24T00:00:00Z",
    "interval": "akshare_daily"
  },
  "600030.SS": {
    "last": 28.4,
    "as_of": "2025-09-24T00:00:00Z",
    "interval": "akshare_daily"
  },
  "600585.SS": {
    "last": 22.98,
    "as_of": "2025-09-24T00:00:00Z",
    "interval": "akshare_daily"
  },
  "600000.SS": {
    "last": 12.24,
    "as_of": "2025-09-24T00:00:00Z",
    "interval": "akshare_daily"
  },
  "601601.SS": {
    "last": 34.71,
    "as_of": "2025-09-24T00:00:00Z",
    "interval": "akshare_daily"
  },
  "601939.SS": {
    "last": 8.77,
    "as_of": "2025-09-24T00:00:00Z",
    "interval": "akshare_daily"
  },
  "600019.SS": {
    "last": 6.84,
    "as_of": "2025-09-24T00:00:00Z",
    "interval": "akshare_daily"
  },
  "600276.SS": {
    "last": 69.82,
    "as_of": "2025-09-24T00:00:00Z",
    "interval": "akshare_daily"
  },
  "601766.SS": {
    "last": 7.42,
    "as_of": "2025-09-24T00:00:00Z",
    "interval": "akshare_daily"
  },
  "600309.SS": {
    "last": 63.27,
    "as_of": "2025-09-24T00:00:00Z",
    "interval": "akshare_daily"
  },
  "601633.SS": {
    "last": 24.6,
    "as_of": "2025-09-24T00:00:00Z",
    "interval": "akshare_daily"
  },
  "600887.SS": {
    "last": 27.39,
    "as_of": "2025-09-24T00:00:00Z",
    "interval": "akshare_daily"
  },
  "601668.SS": {
    "last": 5.51,
    "as_of": "2025-09-24T00:00:00Z",
    "interval": "akshare_daily"
  },
  "601658.SS": {
    "last": 6.07,
    "as_of": "2025-09-24T00:00:00Z",
    "interval": "akshare_daily"
  },
  "601728.SS": {
    "last": 6.7,
    "as_of": "2025-09-24T00:00:00Z",
    "interval": "akshare_daily"
  },
  "601628.SS": {
    "last": 37.83,
    "as_of": "2025-09-24T00:00:00Z",
    "interval": "akshare_daily"
  },
  "688981.SS": {
    "last": 135.81,
    "as_of": "2025-09-24T00:00:00Z",
    "interval": "akshare_daily"
  },
  "^GDAXI": {
    "last": 23652.94921875,
    "as_of": "2025-09-23T14:26:50Z",
    "interval": "yahoo_1d"
  },
  "meta": {
    "generated_at": "2025-09-24T05:21:57Z",
    "source": "Finnhub(/quote) for US; Akshare for CN; Yahoo for EU/JP/SA/Crypto/FX/Commodities/Indices",
    "note": "Never writes nulls; preserves previous values if unavailable."
  }
}