{
  "AAPL": {
    "last": 237.7,
    "as_of": "2025-09-18T18:44:12Z",
    "interval": "finnhub"
  },
  "MSFT": {
    "last": 508.215,
    "as_of": "2025-09-18T18:44:10Z",
    "interval": "finnhub"
  },
  "AMZN": {
    "last": 231.605,
    "as_of": "2025-09-18T18:44:10Z",
    "interval": "finnhub"
  },
  "GOOGL": {
    "last": 251.61,
    "as_of": "2025-09-18T18:44:11Z",
    "interval": "finnhub"
  },
  "NVDA": {
    "last": 176.61,
    "as_of": "2025-09-18T18:44:11Z",
    "interval": "finnhub"
  },
  "TSLA": {
    "last": 423.1827,
    "as_of": "2025-09-18T18:44:11Z",
    "interval": "finnhub"
  },
  "meta": {
    "generated_at": "2025-09-18T18:44:20Z",
    "source": "finnhub /quote",
    "note": "Official provider only; never writes nulls; preserves previous values if unavailable."
  }
}