{
  "AAPL": {
    "last": 263.2608,
    "as_of": "2025-10-24T19:20:13Z",
    "interval": "finnhub"
  },
  "MSFT": {
    "last": 524.895,
    "as_of": "2025-10-24T19:20:11Z",
    "interval": "finnhub"
  },
  "NVDA": {
    "last": 186.89,
    "as_of": "2025-10-24T19:20:13Z",
    "interval": "finnhub"
  },
  "AMZN": {
    "last": 224.2501,
    "as_of": "2025-10-24T19:20:13Z",
    "interval": "finnhub"
  },
  "GOOGL": {
    "last": 260.59,
    "as_of": "2025-10-24T19:20:13Z",
    "interval": "finnhub"
  },
  "GOOG": {
    "last": 261.33,
    "as_of": "2025-10-24T19:20:13Z",
    "interval": "finnhub"
  },
  "META": {
    "last": 739.7399,
    "as_of": "2025-10-24T19:20:13Z",
    "interval": "finnhub"
  },
  "AVGO": {
    "last": 356.25,
    "as_of": "2025-10-24T19:20:13Z",
    "interval": "finnhub"
  },
  "LLY": {
    "last": 832.6,
    "as_of": "2025-10-24T19:19:45Z",
    "interval": "finnhub"
  },
  "TSLA": {
    "last": 431.78,
    "as_of": "2025-10-24T19:20:13Z",
    "interval": "finnhub"
  },
  "JPM": {
    "last": 300.87,
    "as_of": "2025-10-24T19:20:07Z",
    "interval": "finnhub"
  },
  "V": {
    "last": 348.18,
    "as_of": "2025-10-24T19:20:07Z",
    "interval": "finnhub"
  },
  "XOM": {
    "last": 115.29,
    "as_of": "2025-10-24T19:20:12Z",
    "interval": "finnhub"
  },
  "UNH": {
    "last": 363.54,
    "as_of": "2025-10-24T19:20:08Z",
    "interval": "finnhub"
  },
  "JNJ": {
    "last": 190.648,
    "as_of": "2025-10-24T19:20:08Z",
    "interval": "finnhub"
  },
  "WMT": {
    "last": 106.15,
    "as_of": "2025-10-24T19:20:12Z",
    "interval": "finnhub"
  },
  "MA": {
    "last": 574.96,
    "as_of": "2025-10-24T19:19:55Z",
    "interval": "finnhub"
  },
  "PG": {
    "last": 152.415,
    "as_of": "2025-10-24T19:20:07Z",
    "interval": "finnhub"
  },
  "ORCL": {
    "last": 284.6,
    "as_of": "2025-10-24T19:20:11Z",
    "interval": "finnhub"
  },
  "COST": {
    "last": 931.51,
    "as_of": "2025-10-24T19:19:59Z",
    "interval": "finnhub"
  },
  "MRK": {
    "last": 87.545,
    "as_of": "2025-10-24T19:20:13Z",
    "interval": "finnhub"
  },
  "HD": {
    "last": 387.01,
    "as_of": "2025-10-24T19:20:11Z",
    "interval": "finnhub"
  },
  "KO": {
    "last": 69.825,
    "as_of": "2025-10-24T19:20:10Z",
    "interval": "finnhub"
  },
  "PEP": {
    "last": 151.56,
    "as_of": "2025-10-24T19:20:11Z",
    "interval": "finnhub"
  },
  "BAC": {
    "last": 52.56,
    "as_of": "2025-10-24T19:20:11Z",
    "interval": "finnhub"
  },
  "ADBE": {
    "last": 354.04,
    "as_of": "2025-10-24T19:20:03Z",
    "interval": "finnhub"
  },
  "CRM": {
    "last": 254.99,
    "as_of": "2025-10-24T19:20:12Z",
    "interval": "finnhub"
  },
  "NFLX": {
    "last": 1098.629,
    "as_of": "2025-10-24T19:20:10Z",
    "interval": "finnhub"
  },
  "CSCO": {
    "last": 70.725,
    "as_of": "2025-10-24T19:20:13Z",
    "interval": "finnhub"
  },
  "AMD": {
    "last": 251.3815,
    "as_of": "2025-10-24T19:20:13Z",
    "interval": "finnhub"
  },
  "BTC-USD": {
    "last": 118932.6953125,
    "as_of": "2025-10-02T04:12:00Z",
    "interval": "yahoo_1d"
  },
  "DAI-USD": {
    "last": 0.9998124837875366,
    "as_of": "2025-09-30T03:45:00Z",
    "interval": "yahoo_1d"
  },
  "^DJI": {
    "last": 46694.96875,
    "as_of": "2025-10-06T13:30:00Z",
    "interval": "yahoo_1d"
  },
  "^IXIC": {
    "last": 22941.669921875,
    "as_of": "2025-10-06T13:30:00Z",
    "interval": "yahoo_1d"
  },
  "^GDAXI": {
    "last": 23652.94921875,
    "as_of": "2025-09-23T14:26:50Z",
    "interval": "yahoo_1d"
  },
  "meta": {
    "generated_at": "2025-10-24T19:29:38Z",
    "source": "Finnhub(/quote) for US; Akshare for CN; Yahoo for EU/JP/SA/Crypto/FX/Commodities/Indices",
    "note": "Never writes nulls; preserves previous values if unavailable."
  }
}