{
  "AAPL": {
    "last": 237.91,
    "as_of": "2025-09-18T20:00:00Z",
    "interval": "finnhub"
  },
  "MSFT": {
    "last": 508.428,
    "as_of": "2025-09-18T20:00:00Z",
    "interval": "finnhub"
  },
  "AMZN": {
    "last": 231.23,
    "as_of": "2025-09-18T20:00:00Z",
    "interval": "finnhub"
  },
  "GOOGL": {
    "last": 252.059,
    "as_of": "2025-09-18T20:00:00Z",
    "interval": "finnhub"
  },
  "NVDA": {
    "last": 176.32,
    "as_of": "2025-09-18T20:00:00Z",
    "interval": "finnhub"
  },
  "TSLA": {
    "last": 416.85,
    "as_of": "2025-09-18T20:00:00Z",
    "interval": "finnhub"
  },
  "meta": {
    "generated_at": "2025-09-18T20:15:34Z",
    "source": "finnhub /quote",
    "note": "Official provider only; never writes nulls; preserves previous values if unavailable."
  }
}